CHANGELOG
LICENSE
MANIFEST.in
README.md
setup.py
docs/source/conf.py
docs/source/configure.rst
docs/source/customize.rst
docs/source/index.rst
docs/source/install.rst
src/nose2_contrib/__init__.py
src/nose2_contrib/jira/__init__.py
src/nose2_contrib/jira/_version.py
src/nose2_contrib/jira/callbacks.py
src/nose2_contrib/jira/issue_feeders.py
src/nose2_contrib/jira/jira_plugin.py
src/nose2_jira_plugin.egg-info/PKG-INFO
src/nose2_jira_plugin.egg-info/SOURCES.txt
src/nose2_jira_plugin.egg-info/dependency_links.txt
src/nose2_jira_plugin.egg-info/requires.txt
src/nose2_jira_plugin.egg-info/top_level.txt