Metadata-Version: 1.1
Name: nose2-jira-plugin
Version: 1.1.1
Summary: A nose2 test runner plugin to deal with jira bugtracker
Home-page: https://github.com/artragis/nose2-jira-plugin
Author: François (artragis) Dambrine
Author-email: artragis@gmail.com
License: MIT
Keywords: unittest,testing,tests
Platform: UNKNOWN
Classifier: Development Status :: 4 - Beta
Classifier: Environment :: Console
Classifier: Intended Audience :: Developers
Classifier: License :: OSI Approved :: BSD License
Classifier: Programming Language :: Python
Classifier: Programming Language :: Python :: 3.4
Classifier: Programming Language :: Python :: 3.5
Classifier: Programming Language :: Python :: 3.6
Classifier: Programming Language :: Python :: Implementation :: CPython
Classifier: Operating System :: OS Independent
Classifier: Topic :: Software Development :: Libraries
Classifier: Topic :: Software Development :: Libraries :: Python Modules
Classifier: Topic :: Software Development :: Testing
